FIFO.v
module FIFO #(
    parameter DATA_WIDTH = 8,
    parameter ADDR_WIDTH = 4,
    parameter DEPTH = 16
) (
    input  wire                  clk,
    input  wire                  rst,
    input  wire                  wr_en,
    input  wire                  rd_en,
    input  wire [DATA_WIDTH-1:0] data_in,
    
    output wire [DATA_WIDTH-1:0] data_out,
    output wire                  full,
    output wire                  empty
);
    

    reg [DATA_WIDTH-1:0] mem [0:DEPTH-1];
    reg [ADDR_WIDTH:0] w_ptr, r_ptr;

    always @(posedge clk) begin
        if (rst) begin
            w_ptr <= 0;
            r_ptr <= 0;
        end else begin
            if (wr_en && !full) begin 

                mem[w_ptr[ADDR_WIDTH-1:0]] <= data_in;
                w_ptr <= w_ptr + 1'b1;
            end
            
            if (rd_en && !empty) begin 
                r_ptr <= r_ptr + 1'b1;
            end

        end
    end
    assign empty = (w_ptr == r_ptr);
    assign full = (w_ptr[ADDR_WIDTH] != r_ptr[ADDR_WIDTH]) && (w_ptr[ADDR_WIDTH-1:0] == r_ptr[ADDR_WIDTH-1:0]);
    assign data_out = mem[r_ptr[ADDR_WIDTH-1:0]];
endmodule

FIFO_tb.v
`timescale 1ns/1ps

module FIFO_tb;

parameter DATA_WIDTH = 8, ADDR_WIDTH = 4;

reg clk, rst, wr_en, rd_en;
reg [DATA_WIDTH-1:0] data_in;
wire [DATA_WIDTH-1:0] data_out;
wire full, empty;

FIFO #(DATA_WIDTH, ADDR_WIDTH) uut (
    .clk(clk), .rst(rst), .wr_en(wr_en), 
    .rd_en(rd_en), .data_in(data_in), .data_out(data_out), 
    .full(full), .empty(empty)
);

always #50 clk = ~clk;

initial begin 
    $dumpfile("fifo_test.vcd"); 
    $dumpvars(0, FIFO_tb);

    clk = 0;
    rst = 1;
    wr_en <= 0;
    rd_en <= 0;
    data_in = 0;
    
    #150 rst = 0; 

    
    @(posedge clk) begin
        wr_en <= 1;
        data_in <= 8'h1F;
        @(posedge clk) data_in <= 8'h23;
        @(posedge clk) data_in <= 8'h5A;
        @(posedge clk) data_in <= 8'hB1;
        @(posedge clk) data_in <= 8'hB2;
        @(posedge clk) data_in <= 8'hB3;
        @(posedge clk) data_in <= 8'hB4;
        @(posedge clk) wr_en <= 0; 

    end

    #200; 

   
    

    #200; 
    
   
    @(posedge clk) rd_en = 1;
    @(posedge clk);
    @(posedge clk);
    @(posedge clk);
    @(posedge clk) rd_en = 0;  


    
    #1000; 
    $display("Testbench finished!");
    $finish;
end 
    
endmodule

fifo_test.vcd
$date
	Tue Apr  7 09:59:45 2026
$end
$version
	Icarus Verilog
$end
$timescale
	1ps
$end
$scope module FIFO_tb $end
$var wire 1 ! full $end
$var wire 1 " empty $end
$var wire 8 # data_out [7:0] $end
$var parameter 32 $ ADDR_WIDTH $end
$var parameter 32 % DATA_WIDTH $end
$var reg 1 & clk $end
$var reg 8 ' data_in [7:0] $end
$var reg 1 ( rd_en $end
$var reg 1 ) rst $end
$var reg 1 * wr_en $end
$scope module uut $end
$var wire 1 & clk $end
$var wire 8 + data_in [7:0] $end
$var wire 8 , data_out [7:0] $end
$var wire 1 ! full $end
$var wire 1 ( rd_en $end
$var wire 1 ) rst $end
$var wire 1 * wr_en $end
$var wire 1 " empty $end
$var parameter 32 - ADDR_WIDTH $end
$var parameter 32 . DATA_WIDTH $end
$var parameter 32 / DEPTH $end
$var reg 5 0 r_ptr [4:0] $end
$var reg 5 1 w_ptr [4:0] $end
$upscope $end
$upscope $end
$enddefinitions $end
$comment Show the parameter values. $end
$dumpall
b10000 /
b1000 .
b100 -
b1000 %
b100 $
$end
#0
$dumpvars
bx 1
bx 0
bx ,
b0 +
0*
1)
0(
b0 '
0&
bx #
x"
x!
$end
#50000
0!
1"
b0 0
b0 1
1&
#100000
0&
#150000
b11111 '
b11111 +
1*
1&
0)
#200000
0&
#250000
b100011 '
b100011 +
0"
b1 1
b11111 #
b11111 ,
1&
#300000
0&
#350000
b10 1
b1011010 '
b1011010 +
1&
#400000
0&
#450000
b10110001 '
b10110001 +
b11 1
1&
#500000
0&
#550000
b100 1
b10110010 '
b10110010 +
1&
#600000
0&
#650000
b10110011 '
b10110011 +
b101 1
1&
#700000
0&
#750000
b110 1
b10110100 '
b10110100 +
1&
#800000
0&
#850000
0*
b111 1
1&
#900000
0&
#950000
1&
#1000000
0&
#1050000
1&
#1100000
0&
#1150000
1&
#1200000
0&
#1250000
b100011 #
b100011 ,
b1 0
1(
1&
#1300000
0&
#1350000
b1011010 #
b1011010 ,
b10 0
1&
#1400000
0&
#1450000
b10110001 #
b10110001 ,
b11 0
1&
#1500000
0&
#1550000
b10110010 #
b10110010 ,
b100 0
1&
#1600000
0&
#1650000
0(
1&
